Program_4/Program_4.v
// Verilog code for full adder
module full_adder(input a,input b,input cin,output sum,output cout);

 wire p,q,r;
   xor(sum,a,b,cin);
   xor(p,a,b);
   and(q,a,b);
   and(r,p,cin);
   or(cout,q,r);


endmodule

`timescale 1ns / 1ps
module stimulus;

 reg a,b,cin;
 wire sum,cout;

 full_adder uut(a,b,cin,sum,cout);

 initial begin
  $dumpfile("p4.vcd");
  $dumpvars(0,stimulus);
  $display("A     B   CARRY IN   SUM   CARRY OUT\n");
 
  #0 a = 0;b = 0;cin = 0;
  #10 a = 0;b = 0;cin = 1;
  #10 a = 0;b = 1;cin = 0;
  #10 a = 0;b = 1;cin = 1;
  #10 a = 1;b = 0;cin = 0;
  #10 a = 1;b = 0;cin = 1;
  #10 a = 1;b = 1;cin = 0;
  #10 a = 1;b = 1;cin = 1;
  #10;

 end

 initial begin

   $monitor("%d     %d      %d       %d     %d\n",a,b,cin,sum,cout);

 end

endmodule

Program_4/Program_4.vcd
$date
	Sun Oct 15 23:57:18 2017
$end
$version
	Icarus Verilog
$end
$timescale
	1ps
$end
$scope module stimulus $end
$var wire 1 ! cout $end
$var wire 1 " sum $end
$var reg 1 # a $end
$var reg 1 $ b $end
$var reg 1 % cin $end
$scope module uut $end
$var wire 1 & a $end
$var wire 1 ' b $end
$var wire 1 ( cin $end
$var wire 1 ! cout $end
$var wire 1 ) p $end
$var wire 1 * q $end
$var wire 1 + r $end
$var wire 1 " sum $end
$upscope $end
$upscope $end
$enddefinitions $end
#0
$dumpvars
0+
0*
0)
0(
0'
0&
0%
0$
0#
0"
0!
$end
#10000
1"
1%
1(
#20000
1)
0%
0(
1$
1'
#30000
1!
0"
1+
1%
1(
#40000
0!
0+
1"
0%
0(
0$
0'
1#
1&
#50000
1!
0"
1+
1%
1(
#60000
0+
0)
1*
0%
0(
1$
1'
#70000
1"
1%
1(
