Program_2/Program_2.v
// Verilog code for encoder and decoder - 16 bit input,4 bit output encoder / 4 bit input, 16 bit output decoder
module decoder(input [4:1]x,output reg[15:0]y);
 
always @ *
 case(x)
 
 0:  y = 1;
 1:  y = 2;
 2:  y = 4;
 3:  y = 8;
 4:  y = 16;
 5:  y = 32;
 6:  y = 64;
 7:  y = 128;
 8:  y = 256;
 9:  y = 512;
 10:  y = 1024;
 11:  y = 2048;
 12:  y = 4096;
 13:  y = 8192;
 14:  y = 16384;
 15:  y = 32768;
 
 endcase
endmodule

module encoder(input [15:0]x,output reg[4:1]y);

always @ * 
 case(x)

 1:  y = 0;
 2:  y = 1;
 4:  y = 2;
 8:  y = 3;
 16:  y = 4;
 32:  y = 5;
 64:  y = 6;
 128:  y = 7;
 256:  y = 8;
 512:  y = 9;
 1024:  y = 10;
 2048:  y = 11;
 4096:  y = 12;
 8192:  y = 13;
 16384:  y = 14;
 32768:  y = 15;

 endcase
endmodule

`timescale 1ns / 1ps 
module stimulus;

 reg [4:1]x;
 reg [15:0]y;
 wire [4:1]p;
 wire [15:0]q;

 encoder uut1(y,p);
 decoder uut2(x,q);

 initial begin
 
  $dumpfile("p2.vcd");
  $dumpvars(0,stimulus); 
   $display("    Encoder \n");
   $display("Input                Encoded data\n"); 
      
 
  #0 y = 1;

  repeat(16)
   begin
     #10 $display("%16b     %4b\n",y,p); 
     y = y*2;
   end
  
  $display("\n   Decoder  \n");
  $display("Encoded data          Output\n");
  
  #0 x = 0;


  repeat(16)
   begin 
    #10 $display("%4b      %16b\n",x,q);
    x = x+1;
   end
 end
endmodule

Program_2/Program_2.vcd
$date
	Sun Oct 15 23:35:33 2017
$end
$version
	Icarus Verilog
$end
$timescale
	1ps
$end
$scope module stimulus $end
$var wire 4 ! p [4:1] $end
$var wire 16 " q [15:0] $end
$var reg 4 # x [4:1] $end
$var reg 16 $ y [15:0] $end
$scope module uut1 $end
$var wire 16 % x [15:0] $end
$var reg 4 & y [4:1] $end
$upscope $end
$scope module uut2 $end
$var wire 4 ' x [4:1] $end
$var reg 16 ( y [15:0] $end
$upscope $end
$upscope $end
$enddefinitions $end
#0
$dumpvars
bx (
bx '
b0 &
b1 %
b1 $
bx #
bx "
b0 !
$end
#10000
b1 &
b1 !
b10 $
b10 %
#20000
b10 &
b10 !
b100 $
b100 %
#30000
b11 &
b11 !
b1000 $
b1000 %
#40000
b100 &
b100 !
b10000 $
b10000 %
#50000
b101 &
b101 !
b100000 $
b100000 %
#60000
b110 &
b110 !
b1000000 $
b1000000 %
#70000
b111 &
b111 !
b10000000 $
b10000000 %
#80000
b1000 &
b1000 !
b100000000 $
b100000000 %
#90000
b1001 &
b1001 !
b1000000000 $
b1000000000 %
#100000
b1010 &
b1010 !
b10000000000 $
b10000000000 %
#110000
b1011 &
b1011 !
b100000000000 $
b100000000000 %
#120000
b1100 &
b1100 !
b1000000000000 $
b1000000000000 %
#130000
b1101 &
b1101 !
b10000000000000 $
b10000000000000 %
#140000
b1110 &
b1110 !
b100000000000000 $
b100000000000000 %
#150000
b1111 &
b1111 !
b1000000000000000 $
b1000000000000000 %
#160000
b1 (
b1 "
b0 #
b0 '
b0 $
b0 %
#170000
b10 (
b10 "
b1 #
b1 '
#180000
b100 (
b100 "
b10 #
b10 '
#190000
b1000 (
b1000 "
b11 #
b11 '
#200000
b10000 (
b10000 "
b100 #
b100 '
#210000
b100000 (
b100000 "
b101 #
b101 '
#220000
b1000000 (
b1000000 "
b110 #
b110 '
#230000
b10000000 (
b10000000 "
b111 #
b111 '
#240000
b100000000 (
b100000000 "
b1000 #
b1000 '
#250000
b1000000000 (
b1000000000 "
b1001 #
b1001 '
#260000
b10000000000 (
b10000000000 "
b1010 #
b1010 '
#270000
b100000000000 (
b100000000000 "
b1011 #
b1011 '
#280000
b1000000000000 (
b1000000000000 "
b1100 #
b1100 '
#290000
b10000000000000 (
b10000000000000 "
b1101 #
b1101 '
#300000
b100000000000000 (
b100000000000000 "
b1110 #
b1110 '
#310000
b1000000000000000 (
b1000000000000000 "
b1111 #
b1111 '
#320000
b1 (
b1 "
b0 #
b0 '
