Program_1/Program_1.v
/*
A hello world message is printed out by a module periodically. The module prints the current timestamp (in clock cycles). Module terminates after 100 clock cycles.
Name: Amal Byju
Roll Number: 16CO205
Date: 01/08/2017
*/
`timescale 1ns / 1ps
module hello_world;

 reg clock;
 integer i;  

 initial begin
 
  $dumpfile("p1.vcd");
  $dumpvars(0,hello_world);
  
  #0 clock = 0;i = 0;
   
  repeat(100)
   begin
    #10 clock = ~clock; 
    #10 clock = ~clock;i = i+1;
    $display("Hello World   Current Timestamp: %d\n",i);
   end
 end
endmodule

Program_1/Program_1.vcd
$date
	Mon Oct 16 15:12:22 2017
$end
$version
	Icarus Verilog
$end
$timescale
	1ps
$end
$scope module hello_world $end
$var reg 1 ! clock $end
$var integer 32 " i [31:0] $end
$upscope $end
$enddefinitions $end
#0
$dumpvars
b0 "
0!
$end
#10000
1!
#20000
b1 "
0!
#30000
1!
#40000
b10 "
0!
#50000
1!
#60000
b11 "
0!
#70000
1!
#80000
b100 "
0!
#90000
1!
#100000
b101 "
0!
#110000
1!
#120000
b110 "
0!
#130000
1!
#140000
b111 "
0!
#150000
1!
#160000
b1000 "
0!
#170000
1!
#180000
b1001 "
0!
#190000
1!
#200000
b1010 "
0!
#210000
1!
#220000
b1011 "
0!
#230000
1!
#240000
b1100 "
0!
#250000
1!
#260000
b1101 "
0!
#270000
1!
#280000
b1110 "
0!
#290000
1!
#300000
b1111 "
0!
#310000
1!
#320000
b10000 "
0!
#330000
1!
#340000
b10001 "
0!
#350000
1!
#360000
b10010 "
0!
#370000
1!
#380000
b10011 "
0!
#390000
1!
#400000
b10100 "
0!
#410000
1!
#420000
b10101 "
0!
#430000
1!
#440000
b10110 "
0!
#450000
1!
#460000
b10111 "
0!
#470000
1!
#480000
b11000 "
0!
#490000
1!
#500000
b11001 "
0!
#510000
1!
#520000
b11010 "
0!
#530000
1!
#540000
b11011 "
0!
#550000
1!
#560000
b11100 "
0!
#570000
1!
#580000
b11101 "
0!
#590000
1!
#600000
b11110 "
0!
#610000
1!
#620000
b11111 "
0!
#630000
1!
#640000
b100000 "
0!
#650000
1!
#660000
b100001 "
0!
#670000
1!
#680000
b100010 "
0!
#690000
1!
#700000
b100011 "
0!
#710000
1!
#720000
b100100 "
0!
#730000
1!
#740000
b100101 "
0!
#750000
1!
#760000
b100110 "
0!
#770000
1!
#780000
b100111 "
0!
#790000
1!
#800000
b101000 "
0!
#810000
1!
#820000
b101001 "
0!
#830000
1!
#840000
b101010 "
0!
#850000
1!
#860000
b101011 "
0!
#870000
1!
#880000
b101100 "
0!
#890000
1!
#900000
b101101 "
0!
#910000
1!
#920000
b101110 "
0!
#930000
1!
#940000
b101111 "
0!
#950000
1!
#960000
b110000 "
0!
#970000
1!
#980000
b110001 "
0!
#990000
1!
#1000000
b110010 "
0!
#1010000
1!
#1020000
b110011 "
0!
#1030000
1!
#1040000
b110100 "
0!
#1050000
1!
#1060000
b110101 "
0!
#1070000
1!
#1080000
b110110 "
0!
#1090000
1!
#1100000
b110111 "
0!
#1110000
1!
#1120000
b111000 "
0!
#1130000
1!
#1140000
b111001 "
0!
#1150000
1!
#1160000
b111010 "
0!
#1170000
1!
#1180000
b111011 "
0!
#1190000
1!
#1200000
b111100 "
0!
#1210000
1!
#1220000
b111101 "
0!
#1230000
1!
#1240000
b111110 "
0!
#1250000
1!
#1260000
b111111 "
0!
#1270000
1!
#1280000
b1000000 "
0!
#1290000
1!
#1300000
b1000001 "
0!
#1310000
1!
#1320000
b1000010 "
0!
#1330000
1!
#1340000
b1000011 "
0!
#1350000
1!
#1360000
b1000100 "
0!
#1370000
1!
#1380000
b1000101 "
0!
#1390000
1!
#1400000
b1000110 "
0!
#1410000
1!
#1420000
b1000111 "
0!
#1430000
1!
#1440000
b1001000 "
0!
#1450000
1!
#1460000
b1001001 "
0!
#1470000
1!
#1480000
b1001010 "
0!
#1490000
1!
#1500000
b1001011 "
0!
#1510000
1!
#1520000
b1001100 "
0!
#1530000
1!
#1540000
b1001101 "
0!
#1550000
1!
#1560000
b1001110 "
0!
#1570000
1!
#1580000
b1001111 "
0!
#1590000
1!
#1600000
b1010000 "
0!
#1610000
1!
#1620000
b1010001 "
0!
#1630000
1!
#1640000
b1010010 "
0!
#1650000
1!
#1660000
b1010011 "
0!
#1670000
1!
#1680000
b1010100 "
0!
#1690000
1!
#1700000
b1010101 "
0!
#1710000
1!
#1720000
b1010110 "
0!
#1730000
1!
#1740000
b1010111 "
0!
#1750000
1!
#1760000
b1011000 "
0!
#1770000
1!
#1780000
b1011001 "
0!
#1790000
1!
#1800000
b1011010 "
0!
#1810000
1!
#1820000
b1011011 "
0!
#1830000
1!
#1840000
b1011100 "
0!
#1850000
1!
#1860000
b1011101 "
0!
#1870000
1!
#1880000
b1011110 "
0!
#1890000
1!
#1900000
b1011111 "
0!
#1910000
1!
#1920000
b1100000 "
0!
#1930000
1!
#1940000
b1100001 "
0!
#1950000
1!
#1960000
b1100010 "
0!
#1970000
1!
#1980000
b1100011 "
0!
#1990000
1!
#2000000
b1100100 "
0!
