Program_7/Program_7.v
// Verilog code for SR flip flop
module sr(input s,input r,output q,output _q);
	assign _q=~(q|s);
	assign q=~(_q|r);
endmodule

module dlatch(input clk,input d,output q,output _q);
	sr s1(d&clk,~d&clk,q,_q);
	
endmodule
	
	
module dflip(input d,input clk,output q,output _q);
	wire temp;
	dlatch d1(~clk,d,temp,);
	dlatch d2(clk,temp,q,_q);
	
	
endmodule

`timescale 1ns/1ps
module stimulus;
	reg d;
	reg clk;
	wire q;
	wire _q;
	dflip uut(d,clk,q,_q);
	initial 
		begin
			$dumpfile("p7.vcd");
			$dumpvars(0,stimulus);
			d=0;
			#8 d=1;
			#12 d=0;
			#14 d=0;
			#10 d=1;
			#40;
		end
	integer i;
	initial
		begin
			clk=0;
			for(i=0;i<8;i=i+1)
				#10 clk=~clk;
		end
	initial
		begin
			#10;
			$monitor("d: %b, q: %b ,clock: %d",d,q,clk);
		end
	
	
	
	
	
		
		
endmodule

Program_7/Program_7.vcd
$date
	Mon Oct 16 00:15:02 2017
$end
$version
	Icarus Verilog
$end
$timescale
	1ps
$end
$scope module stimulus $end
$var wire 1 ! _q $end
$var wire 1 " q $end
$var reg 1 # clk $end
$var reg 1 $ d $end
$var integer 32 % i [31:0] $end
$scope module uut $end
$var wire 1 ! _q $end
$var wire 1 & clk $end
$var wire 1 ' d $end
$var wire 1 " q $end
$var wire 1 ( temp $end
$scope module d1 $end
$var wire 1 ) _q $end
$var wire 1 * clk $end
$var wire 1 ' d $end
$var wire 1 ( q $end
$scope module s1 $end
$var wire 1 ) _q $end
$var wire 1 ( q $end
$var wire 1 + r $end
$var wire 1 , s $end
$upscope $end
$upscope $end
$scope module d2 $end
$var wire 1 ! _q $end
$var wire 1 & clk $end
$var wire 1 ( d $end
$var wire 1 " q $end
$scope module s1 $end
$var wire 1 ! _q $end
$var wire 1 " q $end
$var wire 1 - r $end
$var wire 1 . s $end
$upscope $end
$upscope $end
$upscope $end
$upscope $end
$enddefinitions $end
#0
$dumpvars
0.
0-
0,
1+
1*
1)
0(
0'
0&
b0 %
0$
0#
x"
x!
$end
#8000
1(
0)
0+
1,
1$
1'
#10000
1"
0!
0,
0*
1.
b1 %
1#
1&
#20000
1)
0(
1+
1*
0.
b10 %
0#
0&
0$
0'
#30000
1!
0"
0+
0*
1-
b11 %
1#
1&
#40000
1+
1*
0-
b100 %
0#
0&
#44000
1(
0)
0+
1,
1$
1'
#50000
1"
0!
0,
0*
1.
b101 %
1#
1&
#60000
1,
1*
0.
b110 %
0#
0&
#70000
0,
0*
1.
b111 %
1#
1&
#80000
1,
1*
0.
b1000 %
0#
0&
